{"difficulty": "hard", "playerMovesLeft": 196, "engineMovesLeft": 195, "fileType": "GAMEFILE", "maxTurns": 200, "GAMEDONE": 0, "TPLAYER": "player1", "FPLAYER": "player2", "TPCOLOUR": "B", "FPCOLOUR": "W", "GAMESCORE": 0, "placedPlayerPieces": 4, "placedEnginePieces": 4, "onhandPlayerPieces": 6, "onhandEnginePieces": 7, "totalPiecesPerPlayer": 11, "nodeInfo": {"[0, 0]": {"reachableNodes": [[0, 1], [1, 0], [3, 0]], "marking": "A"}, "[0, 1]": {"reachableNodes": [[0, 0], [0, 2], [1, 1]], "marking": "E"}, "[0, 2]": {"reachableNodes": [[0, 1], [1, 2], [3, 6]], "marking": "P"}, "[1, 0]": {"reachableNodes": [[0, 0], [3, 1], [1, 1]], "marking": "A"}, "[1, 1]": {"reachableNodes": [[0, 1], [1, 0], [1, 2], [2, 1]], "marking": "E"}, "[1, 2]": {"reachableNodes": [[0, 2], [1, 1], [3, 5]], "marking": "E"}, "[2, 0]": {"reachableNodes": [[2, 1], [3, 2]], "marking": "A"}, "[2, 1]": {"reachableNodes": [[1, 1], [2, 0], [2, 2], [3, 3]], "marking": "E"}, "[2, 2]": {"reachableNodes": [[2, 1], [3, 4]], "marking": "A"}, "[3, 0]": {"reachableNodes": [[0, 0], [3, 1], [6, 0]], "marking": "A"}, "[3, 1]": {"reachableNodes": [[1, 0], [3, 0], [3, 2], [5, 0]], "marking": "A"}, "[3, 2]": {"reachableNodes": [[2, 0], [3, 1], [3, 3], [4, 0]], "marking": "A"}, "[3, 3]": {"reachableNodes": [[2, 1], [3, 2], [3, 4], [4, 1]], "marking": "A"}, "[3, 4]": {"reachableNodes": [[2, 2], [3, 3], [3, 5], [4, 2]], "marking": "A"}, "[3, 5]": {"reachableNodes": [[1, 2], [3, 4], [3, 6], [5, 2]], "marking": "A"}, "[3, 6]": {"reachableNodes": [[0, 2], [3, 5], [6, 2]], "marking": "A"}, "[4, 0]": {"reachableNodes": [[3, 2], [4, 1]], "marking": "A"}, "[4, 1]": {"reachableNodes": [[3, 3], [4, 0], [4, 2], [5, 1]], "marking": "P"}, "[4, 2]": {"reachableNodes": [[3, 4], [4, 1]], "marking": "A"}, "[5, 0]": {"reachableNodes": [[3, 1], [5, 1], [6, 0]], "marking": "A"}, "[5, 1]": {"reachableNodes": [[4, 1], [5, 0], [5, 2], [6, 1]], "marking": "A"}, "[5, 2]": {"reachableNodes": [[3, 5], [5, 1], [6, 2]], "marking": "A"}, "[6, 0]": {"reachableNodes": [[3, 0], [5, 0], [6, 1]], "marking": "P"}, "[6, 1]": {"reachableNodes": [[5, 1], [6, 0], [6, 2]], "marking": "A"}, "[6, 2]": {"reachableNodes": [[3, 6], [5, 2], [6, 1]], "marking": "P"}}}